rides_env/__init__.py
rides_env/__init__.pyi
rides_env/entities.py
rides_env/entities.pyi
rides_env/env.py
rides_env/env.pyi
rides_env/instance.py
rides_env/instance.pyi
rides_env/network.py
rides_env/network.pyi
rides_env/py.typed
rides_env/solution.py
rides_env/solution.pyi
rides_env/utils.py
rides_env/utils.pyi
rides_env-0.1.20.dist-info/WHEEL
rides_env-0.1.20.dist-info/METADATA
rides_env-0.1.20.dist-info/RECORD
